<?xml version="1.0" encoding="UTF-8"?>
<entitymodel xmlns:xsi="http://www.w3.org/2001/XMLSchema-instance"
    xsi:noNamespaceSchemaLocation="http://ofbiz.apache.org/dtds/entitymodel.xsd">
    <!-- ========================================================= -->
    <!-- ======================== Defaults ======================= -->
    <!-- ========================================================= -->
    <title>Entity of NormalRemittanceProcessing Component</title>
    <description>None</description>
    <copyright></copyright>
    <version></version>
    
    <entity entity-name="NormalRemittanceMonthYear" package-name="org.ofbiz.normalremittanceprocessing"
		title="Normal Remittance Month Year Entity">
		<field name="normalRemittanceMonthYearId" type="id-vlong-int"></field>
		<field name="isActive" type="indicator"></field>
		<field name="createdBy" type="id"></field>
		<field name="updatedBy" type="name"></field>
		<field name="month" type="id-int"></field>
		<field name="year" type="id-int"></field>
		<field name="stationId" type="id"></field>
		<field name="remittanceNumber" type="id-vlong-int"></field>
		<field name="processed" type="indicator"></field>
		<field name="postingacctgTransId" type="id"   enable-audit-log="true"></field>
		<prim-key field="normalRemittanceMonthYearId"/>
	</entity>
	
	
	<entity entity-name="MemberRemittance" package-name="org.ofbiz.normalremittanceprocessing"
		title="MemberRemittance Entity">
		
		<field name="memberRemittanceId" type="id-vlong-int"></field>
		
		<field name="normalRemittanceMonthYearId" type="id-vlong-int"></field>
		<field name="isActive" type="indicator"></field>
		<field name="createdBy" type="id"></field>
		<field name="month" type="id"></field>
		<field name="year" type="id"></field>
		<field name="employerCode" type="id"></field>
		
		<field name="payrollNumber" type="id"></field>
		<field name="memberNames" type="name"></field>
		<field name="memberDepositsAmount" type="fixed-point"></field>
		<field name="shareCapitalAmount" type="fixed-point"></field>
		<field name="loansInterestInsuranceAmount" type="fixed-point"></field>
		<field name="fosaContributionsAmount" type="fixed-point"></field>
		<field name="juniorAmount" type="fixed-point"></field>
		<field name="holidayAmount" type="fixed-point"></field>
		
		<field name="totalAmount" type="fixed-point"></field>
		<field name="processed" type="indicator"></field>
		<prim-key field="memberRemittanceId"/>
	</entity>
	
	<!-- NormalRemittanceMonthYearDeleted -->
	<!-- entity entity-name="NormalRemittanceMonthYearDeleted" package-name="org.ofbiz.normalremittanceprocessing"
		title="Normal Remittance Month Year Deleted Entity">
		<field name="normalRemittanceMonthYearDeletedId" type="id-vlong-int"></field>
		<field name="normalRemittanceMonthYearId" type="id-vlong-int"></field>
		<field name="isActive" type="indicator"></field>
		<field name="createdBy" type="id"></field>
		<field name="deletedBy" type="id"></field>
		<field name="deletedDate" type="date-time"></field>
		<field name="updatedBy" type="name"></field>
		<field name="month" type="id-int"></field>
		<field name="year" type="id-int"></field>
		<field name="stationId" type="id"></field>
		<field name="remittanceNumber" type="id-vlong-int"></field>
		<field name="processed" type="indicator"></field>
		<field name="postingacctgTransId" type="id"   enable-audit-log="true"></field>
		<prim-key field="normalRemittanceMonthYearDeletedId"/>
	</entity -->
	
	<!-- Normal Remittance Deleted -->
	<entity entity-name="MemberRemittanceDeleted" package-name="org.ofbiz.normalremittanceprocessing"
		title="MemberRemittanceDeleted Entity">
		
		
		<field name="memberRemittanceDeletedId" type="id-vlong-int"></field>
		<field name="memberRemittanceId" type="id-vlong-int"></field>
		
		<field name="normalRemittanceMonthYearId" type="id-vlong-int"></field>
		<field name="isActive" type="indicator"></field>
		<field name="createdBy" type="id"></field>
		<field name="deletedBy" type="id"></field>
		<field name="deletedDate" type="date-time"></field>
		<field name="month" type="id"></field>
		<field name="year" type="id"></field>
		<field name="employerCode" type="id"></field>
		
		<field name="payrollNumber" type="id"></field>
		<field name="memberNames" type="name"></field>
		<field name="memberDepositsAmount" type="fixed-point"></field>
		<field name="shareCapitalAmount" type="fixed-point"></field>
		<field name="loansInterestInsuranceAmount" type="fixed-point"></field>
		<field name="fosaContributionsAmount" type="fixed-point"></field>
		<field name="juniorAmount" type="fixed-point"></field>
		<field name="holidayAmount" type="fixed-point"></field>
		
		<field name="totalAmount" type="fixed-point"></field>
		<field name="processed" type="indicator"></field>
		<prim-key field="memberRemittanceDeletedId"/>
	</entity>
	
	<!-- DividendYear -->
	 <entity entity-name="DividendYear" package-name="org.ofbiz.normalremittanceprocessing"
		title="Dividend Year Entity">
		<field name="dividendYearId" type="id-vlong-int"></field>
		<field name="isActive" type="indicator"></field>
		<field name="createdBy" type="id"></field>
		<field name="updatedBy" type="name"></field>
		<field name="month" type="id-int"></field>
		<field name="year" type="id-int"></field>
		<field name="stationId" type="id"></field>
		<field name="processed" type="indicator"></field>
		<field name="postingacctgTransId" type="id"   enable-audit-log="true"></field>
		<prim-key field="dividendYearId"/>
	</entity>
	
	<entity entity-name="MemberDividend" package-name="org.ofbiz.normalremittanceprocessing"
		title="MemberDividend Entity">
		
		<field name="memberDividendId" type="id-vlong-int"></field>
		
		<field name="dividendYearId" type="id-vlong-int"></field>
		<field name="isActive" type="indicator"></field>
		<field name="createdBy" type="id"></field>
		<field name="year" type="id"></field>
		
		<field name="idNumber" type="id"></field>
		<field name="payrollNumber" type="id"></field>
		<field name="memberNames" type="name"></field>

		<field name="totalAmount" type="fixed-point"></field>
		<field name="processed" type="indicator"></field>
		<prim-key field="memberDividendId"/>
	</entity>
	
	<!-- Missing ID Numbers -->
	<entity entity-name="MemberDividendMissing" package-name="org.ofbiz.normalremittanceprocessing"
		title="MemberDividendMissing Entity">
		
		<field name="memberDividendMissingId" type="id-vlong-int"></field>
		
		<field name="dividendYearId" type="id-vlong-int"></field>
		<field name="isActive" type="indicator"></field>
		<field name="createdBy" type="id"></field>
		<field name="year" type="id"></field>
		
		<field name="idNumber" type="id"></field>
		<field name="payrollNumber" type="id"></field>
		<field name="memberNames" type="name"></field>
		

		<field name="totalAmount" type="fixed-point"></field>
		<field name="processed" type="indicator"></field>
		<prim-key field="memberDividendMissingId"/>
	</entity>
	
	
	<!-- DividendSourceAccount -->
	<entity entity-name="DividendSourceAccount" package-name="org.ofbiz.normalremittanceprocessing"
		title="DividendSourceAccount Entity">
		<field name="dividendSourceAccountId" type="id-vlong-int" enable-audit-log="true"></field>
		
		<field name="isActive" type="indicator" enable-audit-log="true"></field>
		<field name="createdBy" type="name" enable-audit-log="true"></field>
		<field name="updatedBy" type="name" enable-audit-log="true"></field>
		
		<field name="partyId" type="id-vlong-int" enable-audit-log="true"></field>
		<field name="memberAccountId" type="id-vlong-int" enable-audit-log="true"></field>
		
		<prim-key field="dividendSourceAccountId"/>
		<relation type="one" fk-name="DividendSourceAccount_Member" rel-entity-name="Member">
        	<key-map field-name="partyId"/>
      	</relation>
      	<relation type="one" fk-name="DividendSourceAccount_MemberAccount" rel-entity-name="MemberAccount">
        	<key-map field-name="memberAccountId"/>
      	</relation>
	</entity>

</entitymodel>